aiva/__init__.py
aiva_voice-0.1.0.dist-info/METADATA
aiva_voice-0.1.0.dist-info/WHEEL
aiva_voice-0.1.0.dist-info/top_level.txt
aiva_voice-0.1.0.dist-info/RECORD
