Metadata-Version: 2.4
Name: aiva-voice
Version: 0.1.0
Summary: AIVA Voice: Go-to voice solution for AI agents - telephony, TTS, STT
Home-page: https://aiva.help
Author: Midnight Now
Author-email: studio@macagent.pro
Classifier: Programming Language :: Python :: 3
Classifier: License :: OSI Approved :: MIT License
Classifier: Operating System :: OS Independent
Requires-Python: >=3.6
Dynamic: author
Dynamic: author-email
Dynamic: classifier
Dynamic: description
Dynamic: description-content-type
Dynamic: home-page
Dynamic: requires-python
Dynamic: summary
